left_shift_arithmtic_circuit_module.v
module left_shift_arithmtic_circuit_module (A, X);

    input [3:0] A;

    output [3:0] X;
    
    assign X = A << 1;
endmodule

arith_shift.v
`timescale 1ns/1ns
`include "left_shift_arithmtic_circuit_module.v"

module arith_shifter_test;

reg [3:0] A;

wire [3:0] X;

integer i;
left_shift_arithmtic_circuit_module uut (A, X);

initial begin

    $dumpfile ("arith_shifter_test.vcd");// holds output waveform
    $dumpvars (0, arith_shifter_test);

    
    i = 0;
    while (i < 16) begin
        A = i;      // Assign A to the binary value of i
        #10;        // Wait 10 time units
        i = i + 1;  // Increment i
    end
 

    /*
    A = 0000;
    #10;

    A = 0001;
    #10;

    A = 0010;
    #10;

    A = 0011;
    #10;

    A = 0100;
    #10;

    A = 0101;
    #10;

    A = 0110;
    #10;

    A = 0111;
    #10;

    A = 1000;
    #10;

    A = 1001;
    #10;

    A = 1010;
    #10;

    A = 1011;
    #10;

    A = 1100;
    #10;

    A = 1101;
    #10;

    A = 1110;
    #10;

    A = 1111;
    #10;
    */

    $display (" Testing arithmetic shifter (shifting left by 1) ");

end

endmodule

arith_shifter_test.vcd
$date
	Sat Feb 08 00:15:10 2025
$end
$version
	Icarus Verilog
$end
$timescale
	1ns
$end
$scope module arith_shifter_test $end
$var wire 4 ! X [3:0] $end
$var reg 4 " A [3:0] $end
$var integer 32 # i [31:0] $end
$scope module uut $end
$var wire 4 $ A [3:0] $end
$var wire 4 % X [3:0] $end
$upscope $end
$upscope $end
$enddefinitions $end
$comment Show the parameter values. $end
$dumpall
$end
#0
$dumpvars
b0 %
b0 $
b0 #
b0 "
b0 !
$end
#10
b10 !
b10 %
b1 "
b1 $
b1 #
#20
b100 !
b100 %
b10 "
b10 $
b10 #
#30
b110 !
b110 %
b11 "
b11 $
b11 #
#40
b1000 !
b1000 %
b100 "
b100 $
b100 #
#50
b1010 !
b1010 %
b101 "
b101 $
b101 #
#60
b1100 !
b1100 %
b110 "
b110 $
b110 #
#70
b1110 !
b1110 %
b111 "
b111 $
b111 #
#80
b0 !
b0 %
b1000 "
b1000 $
b1000 #
#90
b10 !
b10 %
b1001 "
b1001 $
b1001 #
#100
b100 !
b100 %
b1010 "
b1010 $
b1010 #
#110
b110 !
b110 %
b1011 "
b1011 $
b1011 #
#120
b1000 !
b1000 %
b1100 "
b1100 $
b1100 #
#130
b1010 !
b1010 %
b1101 "
b1101 $
b1101 #
#140
b1100 !
b1100 %
b1110 "
b1110 $
b1110 #
#150
b1110 !
b1110 %
b1111 "
b1111 $
b1111 #
#160
b10000 #
